{"frame": [{"groundTruthBox": {"topleft_x": 611, "topleft_y": 16, "downright_x": 652, "downright_y": 60, "objectClass": "car"}, "predictedBox": {"topleft_x": 603, "topleft_y": 23, "downright_x": 647, "downright_y": 59, "objectClass": "car"}, "iou": 0.6262580054894785}, {"groundTruthBox": {"topleft_x": 693, "topleft_y": 51, "downright_x": 757, "downright_y": 107, "objectClass": "car"}, "predictedBox": {"topleft_x": 694, "topleft_y": 56, "downright_x": 757, "downright_y": 108, "objectClass": "car"}, "iou": 0.8829928362960998}, {"groundTruthBox": {"topleft_x": 844, "topleft_y": 94, "downright_x": 947, "downright_y": 189, "objectClass": "car"}, "predictedBox": {"topleft_x": 855, "topleft_y": 110, "downright_x": 951, "downright_y": 201, "objectClass": "car"}, "iou": 0.6487617718869899}, {"groundTruthBox": {"topleft_x": 757, "topleft_y": 380, "downright_x": 958, "downright_y": 647, "objectClass": "car"}, "predictedBox": {"topleft_x": 767, "topleft_y": 405, "downright_x": 994, "downright_y": 719, "objectClass": "car"}, "iou": 0.5883480453972257}, {"groundTruthBox": {"topleft_x": 691, "topleft_y": 5, "downright_x": 739, "downright_y": 48, "objectClass": "car"}, "predictedBox": {"topleft_x": 689, "topleft_y": 7, "downright_x": 733, "downright_y": 36, "objectClass": "car"}, "iou": 0.5821299638989169}, {"groundTruthBox": {"topleft_x": 647, "topleft_y": 3, "downright_x": 680, "downright_y": 23, "objectClass": "car"}, "predictedBox": {"topleft_x": 621, "topleft_y": 12, "downright_x": 662, "downright_y": 40, "objectClass": "car"}, "iou": 0.1103448275862069}, {"groundTruthBox": {"topleft_x": 53, "topleft_y": 1, "downright_x": 138, "downright_y": 25, "objectClass": "car"}, "predictedBox": {"topleft_x": 55, "topleft_y": 1, "downright_x": 133, "downright_y": 22, "objectClass": "car"}, "iou": 0.8083720930232559}, {"groundTruthBox": {"topleft_x": 1170, "topleft_y": 447, "downright_x": 1286, "downright_y": 710, "objectClass": "car"}, "predictedBox": {"topleft_x": 1205, "topleft_y": 453, "downright_x": 1277, "downright_y": 719, "objectClass": "car"}, "iou": 0.5970518307180219}, {"groundTruthBox": {"topleft_x": 1247, "topleft_y": 26, "downright_x": 1271, "downright_y": 81, "objectClass": "person"}, "predictedBox": {"topleft_x": 1253, "topleft_y": 24, "downright_x": 1277, "downright_y": 79, "objectClass": "person"}, "iou": 0.5783540022547914}]}