[{"label": "car", "confidence": 0.6706995368003845, "topleft": {"x": 116, "y": 404}, "bottomright": {"x": 229, "y": 484}}, {"label": "car", "confidence": 0.4852444529533386, "topleft": {"x": 542, "y": 489}, "bottomright": {"x": 665, "y": 589}}, {"label": "car", "confidence": 0.43863075971603394, "topleft": {"x": 875, "y": 336}, "bottomright": {"x": 990, "y": 437}}, {"label": "car", "confidence": 0.4279444217681885, "topleft": {"x": 1523, "y": 379}, "bottomright": {"x": 1628, "y": 482}}, {"label": "car", "confidence": 0.4183836579322815, "topleft": {"x": 386, "y": 454}, "bottomright": {"x": 501, "y": 549}}, {"label": "car", "confidence": 0.3822687566280365, "topleft": {"x": 332, "y": 574}, "bottomright": {"x": 488, "y": 669}}, {"label": "car", "confidence": 0.3681841790676117, "topleft": {"x": 1343, "y": 363}, "bottomright": {"x": 1446, "y": 453}}, {"label": "car", "confidence": 0.35439032316207886, "topleft": {"x": 149, "y": 505}, "bottomright": {"x": 304, "y": 627}}, {"label": "car", "confidence": 0.3161226212978363, "topleft": {"x": 149, "y": 505}, "bottomright": {"x": 304, "y": 627}}, {"label": "car", "confidence": 0.23602664470672607, "topleft": {"x": 614, "y": 318}, "bottomright": {"x": 756, "y": 454}}, {"label": "car", "confidence": 0.22783616185188293, "topleft": {"x": 877, "y": 95}, "bottomright": {"x": 1095, "y": 297}}, {"label": "car", "confidence": 0.16162370145320892, "topleft": {"x": 1221, "y": 135}, "bottomright": {"x": 1316, "y": 212}}, {"label": "car", "confidence": 0.15545107424259186, "topleft": {"x": 382, "y": 457}, "bottomright": {"x": 507, "y": 547}}, {"label": "car", "confidence": 0.14925086498260498, "topleft": {"x": 1494, "y": 256}, "bottomright": {"x": 1587, "y": 336}}, {"label": "car", "confidence": 0.14349162578582764, "topleft": {"x": 617, "y": 365}, "bottomright": {"x": 752, "y": 451}}, {"label": "car", "confidence": 0.11786220222711563, "topleft": {"x": 875, "y": 336}, "bottomright": {"x": 990, "y": 437}}, {"label": "car", "confidence": 0.11687491089105606, "topleft": {"x": 1642, "y": 341}, "bottomright": {"x": 1902, "y": 525}}, {"label": "car", "confidence": 0.11661383509635925, "topleft": {"x": 1135, "y": 84}, "bottomright": {"x": 1214, "y": 159}}, {"label": "car", "confidence": 0.11255265772342682, "topleft": {"x": 543, "y": 490}, "bottomright": {"x": 667, "y": 588}}, {"label": "car", "confidence": 0.10976959019899368, "topleft": {"x": 614, "y": 318}, "bottomright": {"x": 756, "y": 454}}, {"label": "car", "confidence": 0.10666584223508835, "topleft": {"x": 1323, "y": 720}, "bottomright": {"x": 1749, "y": 1047}}, {"label": "car", "confidence": 0.10063465684652328, "topleft": {"x": 332, "y": 574}, "bottomright": {"x": 488, "y": 669}}]