[{"label": "car", "confidence": 0.7965584397315979, "topleft": {"x": 28, "y": 647}, "bottomright": {"x": 204, "y": 766}}, {"label": "car", "confidence": 0.5488326549530029, "topleft": {"x": 1487, "y": 429}, "bottomright": {"x": 1595, "y": 525}}, {"label": "car", "confidence": 0.49393191933631897, "topleft": {"x": 485, "y": 528}, "bottomright": {"x": 629, "y": 612}}, {"label": "car", "confidence": 0.45569267868995667, "topleft": {"x": 295, "y": 466}, "bottomright": {"x": 454, "y": 575}}, {"label": "car", "confidence": 0.43602579832077026, "topleft": {"x": 679, "y": 443}, "bottomright": {"x": 795, "y": 530}}, {"label": "car", "confidence": 0.3750484883785248, "topleft": {"x": 1279, "y": 418}, "bottomright": {"x": 1397, "y": 508}}, {"label": "car", "confidence": 0.2353336215019226, "topleft": {"x": 972, "y": 285}, "bottomright": {"x": 1082, "y": 384}}, {"label": "car", "confidence": 0.2023056596517563, "topleft": {"x": 295, "y": 466}, "bottomright": {"x": 454, "y": 575}}, {"label": "car", "confidence": 0.19772037863731384, "topleft": {"x": 1280, "y": 92}, "bottomright": {"x": 1363, "y": 162}}, {"label": "car", "confidence": 0.1740918606519699, "topleft": {"x": 713, "y": 283}, "bottomright": {"x": 846, "y": 411}}, {"label": "car", "confidence": 0.16677406430244446, "topleft": {"x": 1176, "y": 31}, "bottomright": {"x": 1265, "y": 119}}, {"label": "car", "confidence": 0.16513626277446747, "topleft": {"x": 719, "y": 341}, "bottomright": {"x": 842, "y": 415}}, {"label": "car", "confidence": 0.1581902951002121, "topleft": {"x": 1443, "y": 310}, "bottomright": {"x": 1537, "y": 391}}, {"label": "car", "confidence": 0.13182680308818817, "topleft": {"x": 29, "y": 646}, "bottomright": {"x": 203, "y": 768}}, {"label": "book", "confidence": 0.12370260804891586, "topleft": {"x": 1605, "y": 227}, "bottomright": {"x": 1736, "y": 256}}, {"label": "car", "confidence": 0.12272883206605911, "topleft": {"x": 1454, "y": 455}, "bottomright": {"x": 1502, "y": 503}}, {"label": "car", "confidence": 0.11737555265426636, "topleft": {"x": 934, "y": 51}, "bottomright": {"x": 1161, "y": 257}}, {"label": "car", "confidence": 0.1114012822508812, "topleft": {"x": 682, "y": 440}, "bottomright": {"x": 795, "y": 529}}, {"label": "car", "confidence": 0.10632508248090744, "topleft": {"x": 1387, "y": 644}, "bottomright": {"x": 1786, "y": 1004}}, {"label": "car", "confidence": 0.10326998680830002, "topleft": {"x": 1643, "y": 508}, "bottomright": {"x": 1910, "y": 694}}, {"label": "book", "confidence": 0.10262671858072281, "topleft": {"x": 1603, "y": 201}, "bottomright": {"x": 1746, "y": 235}}, {"label": "car", "confidence": 0.10172968357801437, "topleft": {"x": 20, "y": 736}, "bottomright": {"x": 272, "y": 862}}]