[{"label": "person", "confidence": 0.39, "topleft": {"x": 1253, "y": 25}, "bottomright": {"x": 1279, "y": 80}}, {"label": "car", "confidence": 0.37, "topleft": {"x": 55, "y": 1}, "bottomright": {"x": 132, "y": 22}}, {"label": "car", "confidence": 0.47, "topleft": {"x": 613, "y": 16}, "bottomright": {"x": 656, "y": 45}}, {"label": "car", "confidence": 0.31, "topleft": {"x": 692, "y": 12}, "bottomright": {"x": 722, "y": 35}}, {"label": "car", "confidence": 0.42, "topleft": {"x": 703, "y": 35}, "bottomright": {"x": 747, "y": 78}}, {"label": "car", "confidence": 0.13, "topleft": {"x": 763, "y": 13}, "bottomright": {"x": 914, "y": 150}}, {"label": "car", "confidence": 0.47, "topleft": {"x": 831, "y": 79}, "bottomright": {"x": 915, "y": 158}}, {"label": "car", "confidence": 0.9, "topleft": {"x": 733, "y": 287}, "bottomright": {"x": 890, "y": 475}}, {"label": "car", "confidence": 0.84, "topleft": {"x": 1053, "y": 318}, "bottomright": {"x": 1276, "y": 602}}, {"label": "bus", "confidence": 0.5, "topleft": {"x": 814, "y": 38}, "bottomright": {"x": 920, "y": 146}}, {"label": "train", "confidence": 0.12, "topleft": {"x": 114, "y": 0}, "bottomright": {"x": 891, "y": 719}}]