[{"label": "person", "confidence": 1.0, "topleft": {"x": 192, "y": 299}, "bottomright": {"x": 444, "y": 810}}, {"label": "person", "confidence": 1.0, "topleft": {"x": 824, "y": 325}, "bottomright": {"x": 881, "y": 486}}, {"label": "person", "confidence": 1.0, "topleft": {"x": 1255, "y": 304}, "bottomright": {"x": 1311, "y": 564}}, {"label": "person", "confidence": 1.0, "topleft": {"x": 656, "y": 343}, "bottomright": {"x": 697, "y": 452}}, {"label": "person", "confidence": 1.0, "topleft": {"x": 1152, "y": 337}, "bottomright": {"x": 1204, "y": 479}}, {"label": "person", "confidence": 1.0, "topleft": {"x": 925, "y": 336}, "bottomright": {"x": 981, "y": 487}}, {"label": "person", "confidence": 0.99, "topleft": {"x": 1291, "y": 289}, "bottomright": {"x": 1376, "y": 571}}, {"label": "person", "confidence": 0.98, "topleft": {"x": 1003, "y": 345}, "bottomright": {"x": 1029, "y": 412}}, {"label": "bench", "confidence": 0.96, "topleft": {"x": 611, "y": 552}, "bottomright": {"x": 854, "y": 820}}, {"label": "person", "confidence": 0.93, "topleft": {"x": 709, "y": 347}, "bottomright": {"x": 729, "y": 412}}, {"label": "person", "confidence": 0.89, "topleft": {"x": 360, "y": 337}, "bottomright": {"x": 421, "y": 615}}, {"label": "backpack", "confidence": 0.89, "topleft": {"x": 1325, "y": 344}, "bottomright": {"x": 1394, "y": 443}}, {"label": "person", "confidence": 0.87, "topleft": {"x": 726, "y": 339}, "bottomright": {"x": 751, "y": 414}}, {"label": "person", "confidence": 0.87, "topleft": {"x": 626, "y": 345}, "bottomright": {"x": 654, "y": 416}}, {"label": "person", "confidence": 0.82, "topleft": {"x": 1140, "y": 347}, "bottomright": {"x": 1163, "y": 429}}, {"label": "skateboard", "confidence": 0.76, "topleft": {"x": 1284, "y": 552}, "bottomright": {"x": 1356, "y": 581}}, {"label": "person", "confidence": 0.73, "topleft": {"x": 993, "y": 348}, "bottomright": {"x": 1015, "y": 418}}]