[{"label": "person", "confidence": 0.17, "topleft": {"x": 632, "y": 409}, "bottomright": {"x": 660, "y": 482}}, {"label": "person", "confidence": 0.28, "topleft": {"x": 340, "y": 437}, "bottomright": {"x": 371, "y": 499}}, {"label": "person", "confidence": 0.3, "topleft": {"x": 401, "y": 433}, "bottomright": {"x": 438, "y": 503}}, {"label": "person", "confidence": 0.33, "topleft": {"x": 206, "y": 390}, "bottomright": {"x": 1099, "y": 567}}, {"label": "person", "confidence": 0.2, "topleft": {"x": 748, "y": 429}, "bottomright": {"x": 780, "y": 510}}, {"label": "person", "confidence": 0.24, "topleft": {"x": 837, "y": 425}, "bottomright": {"x": 870, "y": 520}}, {"label": "person", "confidence": 0.71, "topleft": {"x": 973, "y": 416}, "bottomright": {"x": 1036, "y": 593}}, {"label": "person", "confidence": 0.14, "topleft": {"x": 1722, "y": 393}, "bottomright": {"x": 1847, "y": 587}}, {"label": "person", "confidence": 0.45, "topleft": {"x": 2, "y": 438}, "bottomright": {"x": 98, "y": 643}}, {"label": "person", "confidence": 0.71, "topleft": {"x": 118, "y": 414}, "bottomright": {"x": 208, "y": 632}}, {"label": "person", "confidence": 0.72, "topleft": {"x": 0, "y": 399}, "bottomright": {"x": 75, "y": 785}}, {"label": "person", "confidence": 0.79, "topleft": {"x": 1239, "y": 372}, "bottomright": {"x": 1355, "y": 787}}, {"label": "bicycle", "confidence": 0.11, "topleft": {"x": 1295, "y": 625}, "bottomright": {"x": 1364, "y": 766}}, {"label": "bench", "confidence": 0.2, "topleft": {"x": 613, "y": 518}, "bottomright": {"x": 685, "y": 559}}, {"label": "bench", "confidence": 0.33, "topleft": {"x": 572, "y": 503}, "bottomright": {"x": 702, "y": 578}}, {"label": "bench", "confidence": 0.5, "topleft": {"x": 697, "y": 566}, "bottomright": {"x": 947, "y": 653}}, {"label": "bench", "confidence": 0.48, "topleft": {"x": 846, "y": 596}, "bottomright": {"x": 1035, "y": 696}}, {"label": "umbrella", "confidence": 0.15, "topleft": {"x": 1324, "y": 646}, "bottomright": {"x": 1362, "y": 729}}, {"label": "handbag", "confidence": 0.24, "topleft": {"x": 1322, "y": 633}, "bottomright": {"x": 1361, "y": 718}}, {"label": "chair", "confidence": 0.13, "topleft": {"x": 1374, "y": 474}, "bottomright": {"x": 1418, "y": 582}}]