[{"label": "car", "confidence": 0.6539371013641357, "topleft": {"x": 853, "y": 368}, "bottomright": {"x": 966, "y": 455}}, {"label": "car", "confidence": 0.41773173213005066, "topleft": {"x": 1145, "y": 800}, "bottomright": {"x": 1329, "y": 918}}, {"label": "car", "confidence": 0.4011111855506897, "topleft": {"x": 295, "y": 530}, "bottomright": {"x": 474, "y": 671}}, {"label": "car", "confidence": 0.24060143530368805, "topleft": {"x": 786, "y": 774}, "bottomright": {"x": 988, "y": 910}}, {"label": "car", "confidence": 0.23048146069049835, "topleft": {"x": 322, "y": 259}, "bottomright": {"x": 747, "y": 486}}, {"label": "car", "confidence": 0.22954875230789185, "topleft": {"x": 322, "y": 259}, "bottomright": {"x": 747, "y": 486}}, {"label": "car", "confidence": 0.19775739312171936, "topleft": {"x": 892, "y": 253}, "bottomright": {"x": 997, "y": 337}}, {"label": "car", "confidence": 0.17343463003635406, "topleft": {"x": 100, "y": 507}, "bottomright": {"x": 256, "y": 648}}, {"label": "car", "confidence": 0.14873595535755157, "topleft": {"x": 952, "y": 774}, "bottomright": {"x": 1163, "y": 914}}, {"label": "car", "confidence": 0.13650479912757874, "topleft": {"x": 100, "y": 507}, "bottomright": {"x": 256, "y": 648}}, {"label": "aeroplane", "confidence": 0.1342468112707138, "topleft": {"x": 151, "y": 10}, "bottomright": {"x": 1741, "y": 1093}}, {"label": "traffic", "confidence": 0.13338100910186768, "topleft": {"x": 262, "y": 342}, "bottomright": {"x": 315, "y": 438}}, {"label": "car", "confidence": 0.12483682483434677, "topleft": {"x": 741, "y": 383}, "bottomright": {"x": 811, "y": 447}}, {"label": "car", "confidence": 0.11023332923650742, "topleft": {"x": 905, "y": 330}, "bottomright": {"x": 970, "y": 388}}, {"label": "car", "confidence": 0.10567804425954819, "topleft": {"x": 835, "y": 364}, "bottomright": {"x": 886, "y": 419}}, {"label": "car", "confidence": 0.10534925013780594, "topleft": {"x": 639, "y": 868}, "bottomright": {"x": 915, "y": 1015}}, {"label": "car", "confidence": 0.10199533402919769, "topleft": {"x": 295, "y": 521}, "bottomright": {"x": 487, "y": 673}}, {"label": "car", "confidence": 0.10163620859384537, "topleft": {"x": 246, "y": 542}, "bottomright": {"x": 307, "y": 637}}]