[{"label": "car", "confidence": 0.6643173694610596, "topleft": {"x": 241, "y": 470}, "bottomright": {"x": 407, "y": 603}}, {"label": "car", "confidence": 0.49186649918556213, "topleft": {"x": 629, "y": 447}, "bottomright": {"x": 753, "y": 549}}, {"label": "car", "confidence": 0.3944680392742157, "topleft": {"x": 3, "y": 664}, "bottomright": {"x": 146, "y": 788}}, {"label": "car", "confidence": 0.379083514213562, "topleft": {"x": 429, "y": 537}, "bottomright": {"x": 570, "y": 633}}, {"label": "car", "confidence": 0.3025716543197632, "topleft": {"x": 1497, "y": 410}, "bottomright": {"x": 1617, "y": 509}}, {"label": "car", "confidence": 0.2902471125125885, "topleft": {"x": 1300, "y": 392}, "bottomright": {"x": 1416, "y": 488}}, {"label": "car", "confidence": 0.27520692348480225, "topleft": {"x": 937, "y": 299}, "bottomright": {"x": 1050, "y": 406}}, {"label": "car", "confidence": 0.25678199529647827, "topleft": {"x": 668, "y": 322}, "bottomright": {"x": 811, "y": 427}}, {"label": "car", "confidence": 0.23555850982666016, "topleft": {"x": 906, "y": 56}, "bottomright": {"x": 1141, "y": 269}}, {"label": "car", "confidence": 0.2053655982017517, "topleft": {"x": 1150, "y": 35}, "bottomright": {"x": 1253, "y": 136}}, {"label": "car", "confidence": 0.16398747265338898, "topleft": {"x": 1462, "y": 275}, "bottomright": {"x": 1563, "y": 369}}, {"label": "car", "confidence": 0.15753518044948578, "topleft": {"x": 669, "y": 292}, "bottomright": {"x": 813, "y": 426}}, {"label": "car", "confidence": 0.14448562264442444, "topleft": {"x": 1598, "y": 137}, "bottomright": {"x": 1763, "y": 374}}, {"label": "car", "confidence": 0.13543842732906342, "topleft": {"x": 1257, "y": 87}, "bottomright": {"x": 1357, "y": 179}}, {"label": "car", "confidence": 0.12717680633068085, "topleft": {"x": 194, "y": 377}, "bottomright": {"x": 296, "y": 459}}, {"label": "car", "confidence": 0.1182965338230133, "topleft": {"x": 1304, "y": 746}, "bottomright": {"x": 1743, "y": 1032}}, {"label": "car", "confidence": 0.11127575486898422, "topleft": {"x": 417, "y": 431}, "bottomright": {"x": 578, "y": 635}}, {"label": "car", "confidence": 0.10517536848783493, "topleft": {"x": 3, "y": 664}, "bottomright": {"x": 146, "y": 788}}]