[{"label": "car", "confidence": 0.734817624092102, "topleft": {"x": 87, "y": 620}, "bottomright": {"x": 266, "y": 740}}, {"label": "car", "confidence": 0.5604830980300903, "topleft": {"x": 966, "y": 34}, "bottomright": {"x": 1148, "y": 254}}, {"label": "car", "confidence": 0.510940432548523, "topleft": {"x": 344, "y": 440}, "bottomright": {"x": 496, "y": 563}}, {"label": "car", "confidence": 0.43862974643707275, "topleft": {"x": 267, "y": 333}, "bottomright": {"x": 406, "y": 428}}, {"label": "car", "confidence": 0.3501497209072113, "topleft": {"x": 1007, "y": 255}, "bottomright": {"x": 1114, "y": 360}}, {"label": "car", "confidence": 0.28365883231163025, "topleft": {"x": 1467, "y": 436}, "bottomright": {"x": 1581, "y": 544}}, {"label": "car", "confidence": 0.24446138739585876, "topleft": {"x": 1253, "y": 427}, "bottomright": {"x": 1375, "y": 527}}, {"label": "car", "confidence": 0.2341977059841156, "topleft": {"x": 539, "y": 506}, "bottomright": {"x": 665, "y": 591}}, {"label": "car", "confidence": 0.23125915229320526, "topleft": {"x": 1414, "y": 307}, "bottomright": {"x": 1525, "y": 404}}, {"label": "car", "confidence": 0.1602112203836441, "topleft": {"x": 1178, "y": 10}, "bottomright": {"x": 1286, "y": 109}}, {"label": "car", "confidence": 0.1434623897075653, "topleft": {"x": 725, "y": 410}, "bottomright": {"x": 845, "y": 510}}, {"label": "car", "confidence": 0.14005209505558014, "topleft": {"x": 748, "y": 263}, "bottomright": {"x": 877, "y": 392}}, {"label": "car", "confidence": 0.1214463859796524, "topleft": {"x": 1307, "y": 742}, "bottomright": {"x": 1743, "y": 1031}}, {"label": "car", "confidence": 0.11733648180961609, "topleft": {"x": 1301, "y": 55}, "bottomright": {"x": 1396, "y": 147}}, {"label": "car", "confidence": 0.1156112477183342, "topleft": {"x": 36, "y": 711}, "bottomright": {"x": 268, "y": 908}}, {"label": "car", "confidence": 0.11044973134994507, "topleft": {"x": 344, "y": 440}, "bottomright": {"x": 496, "y": 563}}, {"label": "car", "confidence": 0.1052839532494545, "topleft": {"x": 1598, "y": 431}, "bottomright": {"x": 1797, "y": 639}}, {"label": "car", "confidence": 0.10476335138082504, "topleft": {"x": 71, "y": 625}, "bottomright": {"x": 986, "y": 1076}}, {"label": "car", "confidence": 0.10356944799423218, "topleft": {"x": 966, "y": 34}, "bottomright": {"x": 1148, "y": 254}}, {"label": "car", "confidence": 0.10117217153310776, "topleft": {"x": 87, "y": 620}, "bottomright": {"x": 266, "y": 740}}, {"label": "car", "confidence": 0.10052447766065598, "topleft": {"x": 772, "y": 98}, "bottomright": {"x": 953, "y": 309}}]