[{"label": "car", "confidence": 0.6247711777687073, "topleft": {"x": 47, "y": 574}, "bottomright": {"x": 268, "y": 763}}, {"label": "car", "confidence": 0.6104864478111267, "topleft": {"x": 996, "y": 622}, "bottomright": {"x": 1136, "y": 741}}, {"label": "car", "confidence": 0.5960321426391602, "topleft": {"x": 1180, "y": 502}, "bottomright": {"x": 1311, "y": 610}}, {"label": "car", "confidence": 0.5194752216339111, "topleft": {"x": 1298, "y": 597}, "bottomright": {"x": 1439, "y": 731}}, {"label": "car", "confidence": 0.39358508586883545, "topleft": {"x": 955, "y": 314}, "bottomright": {"x": 1060, "y": 398}}, {"label": "car", "confidence": 0.313336044549942, "topleft": {"x": 1428, "y": 287}, "bottomright": {"x": 1621, "y": 573}}, {"label": "car", "confidence": 0.2665090560913086, "topleft": {"x": 501, "y": 498}, "bottomright": {"x": 641, "y": 600}}, {"label": "car", "confidence": 0.25357383489608765, "topleft": {"x": 1087, "y": 236}, "bottomright": {"x": 1183, "y": 322}}, {"label": "car", "confidence": 0.23622223734855652, "topleft": {"x": 1260, "y": 88}, "bottomright": {"x": 1345, "y": 172}}, {"label": "car", "confidence": 0.1697198897600174, "topleft": {"x": 1018, "y": 129}, "bottomright": {"x": 1126, "y": 243}}, {"label": "car", "confidence": 0.16869360208511353, "topleft": {"x": 47, "y": 574}, "bottomright": {"x": 268, "y": 763}}, {"label": "car", "confidence": 0.12620799243450165, "topleft": {"x": 1318, "y": 474}, "bottomright": {"x": 1754, "y": 1039}}, {"label": "car", "confidence": 0.12292376160621643, "topleft": {"x": 159, "y": 811}, "bottomright": {"x": 878, "y": 1086}}, {"label": "car", "confidence": 0.1228770837187767, "topleft": {"x": 875, "y": 239}, "bottomright": {"x": 986, "y": 331}}, {"label": "car", "confidence": 0.11976023018360138, "topleft": {"x": 658, "y": 198}, "bottomright": {"x": 763, "y": 271}}, {"label": "car", "confidence": 0.11300034075975418, "topleft": {"x": 646, "y": 426}, "bottomright": {"x": 779, "y": 530}}, {"label": "person", "confidence": 0.10788604617118835, "topleft": {"x": 48, "y": 616}, "bottomright": {"x": 115, "y": 747}}, {"label": "car", "confidence": 0.10176759958267212, "topleft": {"x": 1283, "y": 828}, "bottomright": {"x": 1494, "y": 1062}}]