[{"label": "car", "confidence": 0.8352581858634949, "topleft": {"x": 1060, "y": 882}, "bottomright": {"x": 1279, "y": 1064}}, {"label": "car", "confidence": 0.7136321067810059, "topleft": {"x": 219, "y": 585}, "bottomright": {"x": 377, "y": 706}}, {"label": "car", "confidence": 0.5903851389884949, "topleft": {"x": 601, "y": 426}, "bottomright": {"x": 760, "y": 555}}, {"label": "car", "confidence": 0.5136384963989258, "topleft": {"x": 696, "y": 152}, "bottomright": {"x": 948, "y": 392}}, {"label": "car", "confidence": 0.4331485629081726, "topleft": {"x": 598, "y": 931}, "bottomright": {"x": 817, "y": 1070}}, {"label": "car", "confidence": 0.3605407774448395, "topleft": {"x": 1061, "y": 252}, "bottomright": {"x": 1162, "y": 341}}, {"label": "car", "confidence": 0.3179949223995209, "topleft": {"x": 361, "y": 396}, "bottomright": {"x": 526, "y": 559}}, {"label": "car", "confidence": 0.2881563603878021, "topleft": {"x": 358, "y": 402}, "bottomright": {"x": 531, "y": 556}}, {"label": "car", "confidence": 0.2872332036495209, "topleft": {"x": 1011, "y": 164}, "bottomright": {"x": 1103, "y": 259}}, {"label": "car", "confidence": 0.2640346586704254, "topleft": {"x": 92, "y": 538}, "bottomright": {"x": 228, "y": 655}}, {"label": "car", "confidence": 0.24566034972667694, "topleft": {"x": 359, "y": 394}, "bottomright": {"x": 531, "y": 552}}, {"label": "car", "confidence": 0.1838245689868927, "topleft": {"x": -2, "y": 668}, "bottomright": {"x": 139, "y": 811}}, {"label": "car", "confidence": 0.14206185936927795, "topleft": {"x": 755, "y": 924}, "bottomright": {"x": 1001, "y": 1076}}, {"label": "car", "confidence": 0.11983766406774521, "topleft": {"x": 1609, "y": 286}, "bottomright": {"x": 1714, "y": 379}}, {"label": "car", "confidence": 0.11924844980239868, "topleft": {"x": 1671, "y": 310}, "bottomright": {"x": 1897, "y": 549}}, {"label": "car", "confidence": 0.1145520731806755, "topleft": {"x": 1685, "y": 22}, "bottomright": {"x": 1859, "y": 272}}, {"label": "car", "confidence": 0.11350549757480621, "topleft": {"x": 1273, "y": 859}, "bottomright": {"x": 1811, "y": 1077}}, {"label": "car", "confidence": 0.10929582267999649, "topleft": {"x": 230, "y": 842}, "bottomright": {"x": 722, "y": 1083}}, {"label": "car", "confidence": 0.10890205949544907, "topleft": {"x": 601, "y": 426}, "bottomright": {"x": 760, "y": 555}}]