[{"label": "person", "confidence": 0.9268795847892761, "topleft": {"x": 1678, "y": 195}, "bottomright": {"x": 1877, "y": 870}}, {"label": "person", "confidence": 0.6850128173828125, "topleft": {"x": 58, "y": 337}, "bottomright": {"x": 112, "y": 449}}, {"label": "person", "confidence": 0.6506857872009277, "topleft": {"x": 752, "y": 330}, "bottomright": {"x": 825, "y": 492}}, {"label": "person", "confidence": 0.41396933794021606, "topleft": {"x": 1152, "y": 344}, "bottomright": {"x": 1200, "y": 475}}, {"label": "person", "confidence": 0.3877875506877899, "topleft": {"x": 1292, "y": 339}, "bottomright": {"x": 1345, "y": 473}}, {"label": "person", "confidence": 0.33595117926597595, "topleft": {"x": 966, "y": 364}, "bottomright": {"x": 1022, "y": 473}}, {"label": "person", "confidence": 0.2908201813697815, "topleft": {"x": 922, "y": 361}, "bottomright": {"x": 974, "y": 474}}, {"label": "person", "confidence": 0.25470441579818726, "topleft": {"x": 838, "y": 335}, "bottomright": {"x": 882, "y": 464}}, {"label": "person", "confidence": 0.2534743547439575, "topleft": {"x": 1032, "y": 345}, "bottomright": {"x": 1065, "y": 429}}, {"label": "person", "confidence": 0.25059813261032104, "topleft": {"x": 14, "y": 338}, "bottomright": {"x": 46, "y": 445}}, {"label": "person", "confidence": 0.22415882349014282, "topleft": {"x": 936, "y": 319}, "bottomright": {"x": 979, "y": 424}}, {"label": "person", "confidence": 0.17212419211864471, "topleft": {"x": 749, "y": 280}, "bottomright": {"x": 824, "y": 391}}, {"label": "person", "confidence": 0.1682298630475998, "topleft": {"x": 942, "y": 311}, "bottomright": {"x": 978, "y": 373}}, {"label": "person", "confidence": 0.15986290574073792, "topleft": {"x": 1086, "y": 341}, "bottomright": {"x": 1116, "y": 417}}, {"label": "person", "confidence": 0.14631713926792145, "topleft": {"x": 981, "y": 332}, "bottomright": {"x": 1012, "y": 411}}, {"label": "person", "confidence": 0.14511224627494812, "topleft": {"x": 84, "y": 335}, "bottomright": {"x": 120, "y": 447}}, {"label": "person", "confidence": 0.14039696753025055, "topleft": {"x": 934, "y": 273}, "bottomright": {"x": 982, "y": 354}}, {"label": "person", "confidence": 0.13812153041362762, "topleft": {"x": 867, "y": 341}, "bottomright": {"x": 911, "y": 453}}, {"label": "person", "confidence": 0.136196106672287, "topleft": {"x": 682, "y": 326}, "bottomright": {"x": 715, "y": 398}}, {"label": "car", "confidence": 0.1354294717311859, "topleft": {"x": 325, "y": 306}, "bottomright": {"x": 567, "y": 453}}, {"label": "person", "confidence": 0.13183240592479706, "topleft": {"x": 911, "y": 280}, "bottomright": {"x": 1022, "y": 486}}, {"label": "bench", "confidence": 0.1304035633802414, "topleft": {"x": 2, "y": 546}, "bottomright": {"x": 224, "y": 945}}, {"label": "person", "confidence": 0.1261550337076187, "topleft": {"x": 716, "y": 302}, "bottomright": {"x": 752, "y": 375}}, {"label": "person", "confidence": 0.1239776760339737, "topleft": {"x": 962, "y": 322}, "bottomright": {"x": 988, "y": 358}}, {"label": "person", "confidence": 0.12338957190513611, "topleft": {"x": 720, "y": 331}, "bottomright": {"x": 747, "y": 397}}, {"label": "person", "confidence": 0.11816396564245224, "topleft": {"x": 957, "y": 344}, "bottomright": {"x": 984, "y": 381}}, {"label": "person", "confidence": 0.11537230014801025, "topleft": {"x": 980, "y": 326}, "bottomright": {"x": 1006, "y": 371}}, {"label": "person", "confidence": 0.11259853839874268, "topleft": {"x": 1017, "y": 359}, "bottomright": {"x": 1058, "y": 459}}, {"label": "person", "confidence": 0.11251987516880035, "topleft": {"x": 1145, "y": 326}, "bottomright": {"x": 1176, "y": 416}}, {"label": "person", "confidence": 0.11078920215368271, "topleft": {"x": 876, "y": 339}, "bottomright": {"x": 909, "y": 399}}, {"label": "bench", "confidence": 0.11016187816858292, "topleft": {"x": 19, "y": 601}, "bottomright": {"x": 403, "y": 716}}, {"label": "person", "confidence": 0.10963203012943268, "topleft": {"x": 1004, "y": 346}, "bottomright": {"x": 1029, "y": 386}}, {"label": "person", "confidence": 0.10888861119747162, "topleft": {"x": 1054, "y": 359}, "bottomright": {"x": 1079, "y": 412}}, {"label": "bench", "confidence": 0.10518448799848557, "topleft": {"x": 31, "y": 665}, "bottomright": {"x": 409, "y": 772}}, {"label": "person", "confidence": 0.10428010672330856, "topleft": {"x": 819, "y": 279}, "bottomright": {"x": 912, "y": 494}}, {"label": "bench", "confidence": 0.10331586748361588, "topleft": {"x": 13, "y": 565}, "bottomright": {"x": 478, "y": 1059}}, {"label": "bench", "confidence": 0.10175059735774994, "topleft": {"x": 26, "y": 721}, "bottomright": {"x": 423, "y": 826}}, {"label": "person", "confidence": 0.10086873173713684, "topleft": {"x": 735, "y": 345}, "bottomright": {"x": 761, "y": 419}}]