[{"label": "person", "confidence": 0.929381251335144, "topleft": {"x": 1330, "y": 230}, "bottomright": {"x": 1474, "y": 607}}, {"label": "person", "confidence": 0.7980625033378601, "topleft": {"x": 676, "y": 298}, "bottomright": {"x": 726, "y": 411}}, {"label": "bench", "confidence": 0.7530875205993652, "topleft": {"x": 247, "y": 618}, "bottomright": {"x": 805, "y": 1011}}, {"label": "person", "confidence": 0.6490293145179749, "topleft": {"x": 775, "y": 289}, "bottomright": {"x": 827, "y": 438}}, {"label": "person", "confidence": 0.6140989661216736, "topleft": {"x": 1134, "y": 307}, "bottomright": {"x": 1187, "y": 413}}, {"label": "person", "confidence": 0.5664147138595581, "topleft": {"x": 920, "y": 312}, "bottomright": {"x": 971, "y": 413}}, {"label": "person", "confidence": 0.39097514748573303, "topleft": {"x": 884, "y": 303}, "bottomright": {"x": 924, "y": 416}}, {"label": "person", "confidence": 0.34395456314086914, "topleft": {"x": 1324, "y": 249}, "bottomright": {"x": 1384, "y": 383}}, {"label": "person", "confidence": 0.3004823923110962, "topleft": {"x": 726, "y": 300}, "bottomright": {"x": 759, "y": 374}}, {"label": "person", "confidence": 0.20197729766368866, "topleft": {"x": 189, "y": 274}, "bottomright": {"x": 277, "y": 432}}, {"label": "person", "confidence": 0.18897593021392822, "topleft": {"x": 815, "y": 304}, "bottomright": {"x": 863, "y": 429}}, {"label": "person", "confidence": 0.18090446293354034, "topleft": {"x": 1035, "y": 302}, "bottomright": {"x": 1066, "y": 364}}, {"label": "person", "confidence": 0.1809009611606598, "topleft": {"x": 967, "y": 305}, "bottomright": {"x": 1011, "y": 399}}, {"label": "person", "confidence": 0.16252893209457397, "topleft": {"x": 590, "y": 301}, "bottomright": {"x": 621, "y": 375}}, {"label": "person", "confidence": 0.15809185802936554, "topleft": {"x": 983, "y": 298}, "bottomright": {"x": 1020, "y": 377}}, {"label": "bench", "confidence": 0.15777572989463806, "topleft": {"x": 223, "y": 429}, "bottomright": {"x": 567, "y": 624}}, {"label": "person", "confidence": 0.14595617353916168, "topleft": {"x": 1049, "y": 306}, "bottomright": {"x": 1075, "y": 360}}, {"label": "bench", "confidence": 0.14486832916736603, "topleft": {"x": 13, "y": 511}, "bottomright": {"x": 712, "y": 1058}}, {"label": "person", "confidence": 0.14155995845794678, "topleft": {"x": 1380, "y": 231}, "bottomright": {"x": 1453, "y": 343}}, {"label": "skateboard", "confidence": 0.1380683034658432, "topleft": {"x": 1346, "y": 569}, "bottomright": {"x": 1457, "y": 610}}, {"label": "person", "confidence": 0.1339927464723587, "topleft": {"x": 619, "y": 296}, "bottomright": {"x": 651, "y": 363}}, {"label": "person", "confidence": 0.13242675364017487, "topleft": {"x": 1013, "y": 309}, "bottomright": {"x": 1040, "y": 361}}, {"label": "person", "confidence": 0.13213658332824707, "topleft": {"x": 899, "y": 295}, "bottomright": {"x": 921, "y": 342}}, {"label": "person", "confidence": 0.13032753765583038, "topleft": {"x": 614, "y": 311}, "bottomright": {"x": 635, "y": 357}}, {"label": "person", "confidence": 0.1297139823436737, "topleft": {"x": 629, "y": 309}, "bottomright": {"x": 658, "y": 376}}, {"label": "person", "confidence": 0.12432551383972168, "topleft": {"x": 579, "y": 311}, "bottomright": {"x": 614, "y": 390}}, {"label": "person", "confidence": 0.12211340665817261, "topleft": {"x": 311, "y": 299}, "bottomright": {"x": 343, "y": 379}}, {"label": "person", "confidence": 0.11742258816957474, "topleft": {"x": 1160, "y": 306}, "bottomright": {"x": 1196, "y": 407}}, {"label": "person", "confidence": 0.11326757073402405, "topleft": {"x": 505, "y": 308}, "bottomright": {"x": 567, "y": 400}}, {"label": "person", "confidence": 0.11259736865758896, "topleft": {"x": 1578, "y": 276}, "bottomright": {"x": 1645, "y": 401}}, {"label": "person", "confidence": 0.11095618456602097, "topleft": {"x": 263, "y": 295}, "bottomright": {"x": 301, "y": 387}}, {"label": "person", "confidence": 0.10907056927680969, "topleft": {"x": 687, "y": 298}, "bottomright": {"x": 712, "y": 344}}, {"label": "bench", "confidence": 0.10798387974500656, "topleft": {"x": 295, "y": 753}, "bottomright": {"x": 646, "y": 911}}, {"label": "person", "confidence": 0.10759875923395157, "topleft": {"x": 1393, "y": 228}, "bottomright": {"x": 1509, "y": 544}}, {"label": "bench", "confidence": 0.107540063560009, "topleft": {"x": 248, "y": 526}, "bottomright": {"x": 593, "y": 664}}, {"label": "bench", "confidence": 0.1062186136841774, "topleft": {"x": 265, "y": 596}, "bottomright": {"x": 629, "y": 721}}, {"label": "bench", "confidence": 0.10601451992988586, "topleft": {"x": 420, "y": 723}, "bottomright": {"x": 819, "y": 832}}, {"label": "bench", "confidence": 0.10562217235565186, "topleft": {"x": 284, "y": 823}, "bottomright": {"x": 632, "y": 967}}, {"label": "person", "confidence": 0.10351546108722687, "topleft": {"x": 1101, "y": 316}, "bottomright": {"x": 1125, "y": 373}}, {"label": "person", "confidence": 0.10185513645410538, "topleft": {"x": 901, "y": 276}, "bottomright": {"x": 924, "y": 312}}, {"label": "bench", "confidence": 0.10109300911426544, "topleft": {"x": 297, "y": 472}, "bottomright": {"x": 672, "y": 605}}, {"label": "bench", "confidence": 0.10100866854190826, "topleft": {"x": 34, "y": 750}, "bottomright": {"x": 442, "y": 1047}}, {"label": "person", "confidence": 0.1000332236289978, "topleft": {"x": 929, "y": 295}, "bottomright": {"x": 955, "y": 342}}]