[{"label": "person", "confidence": 0.7802999019622803, "topleft": {"x": 873, "y": 424}, "bottomright": {"x": 930, "y": 581}}, {"label": "person", "confidence": 0.648959755897522, "topleft": {"x": 816, "y": 415}, "bottomright": {"x": 849, "y": 534}}, {"label": "person", "confidence": 0.5013584494590759, "topleft": {"x": 732, "y": 410}, "bottomright": {"x": 770, "y": 527}}, {"label": "person", "confidence": 0.3405248820781708, "topleft": {"x": 1519, "y": 350}, "bottomright": {"x": 1737, "y": 1026}}, {"label": "bench", "confidence": 0.28650420904159546, "topleft": {"x": 599, "y": 588}, "bottomright": {"x": 938, "y": 726}}, {"label": "person", "confidence": 0.2508317530155182, "topleft": {"x": 468, "y": 408}, "bottomright": {"x": 511, "y": 495}}, {"label": "person", "confidence": 0.24546551704406738, "topleft": {"x": -1, "y": 410}, "bottomright": {"x": 67, "y": 604}}, {"label": "person", "confidence": 0.2244408279657364, "topleft": {"x": 48, "y": 407}, "bottomright": {"x": 121, "y": 593}}, {"label": "person", "confidence": 0.20023728907108307, "topleft": {"x": 89, "y": 256}, "bottomright": {"x": 380, "y": 994}}, {"label": "person", "confidence": 0.19816987216472626, "topleft": {"x": 686, "y": 407}, "bottomright": {"x": 714, "y": 489}}, {"label": "person", "confidence": 0.185687854886055, "topleft": {"x": 436, "y": 411}, "bottomright": {"x": 454, "y": 459}}, {"label": "person", "confidence": 0.1759416162967682, "topleft": {"x": 1843, "y": 319}, "bottomright": {"x": 1919, "y": 478}}, {"label": "person", "confidence": 0.17023567855358124, "topleft": {"x": 517, "y": 406}, "bottomright": {"x": 545, "y": 492}}, {"label": "person", "confidence": 0.16734579205513, "topleft": {"x": 573, "y": 389}, "bottomright": {"x": 607, "y": 486}}, {"label": "person", "confidence": 0.1645810902118683, "topleft": {"x": 382, "y": 421}, "bottomright": {"x": 402, "y": 459}}, {"label": "person", "confidence": 0.15909618139266968, "topleft": {"x": 399, "y": 419}, "bottomright": {"x": 417, "y": 446}}, {"label": "person", "confidence": 0.15346652269363403, "topleft": {"x": 784, "y": 420}, "bottomright": {"x": 807, "y": 489}}, {"label": "person", "confidence": 0.12877841293811798, "topleft": {"x": 333, "y": 402}, "bottomright": {"x": 358, "y": 451}}, {"label": "person", "confidence": 0.12752047181129456, "topleft": {"x": 356, "y": 413}, "bottomright": {"x": 373, "y": 443}}, {"label": "person", "confidence": 0.1243334710597992, "topleft": {"x": 447, "y": 427}, "bottomright": {"x": 465, "y": 472}}, {"label": "person", "confidence": 0.12164385616779327, "topleft": {"x": 365, "y": 424}, "bottomright": {"x": 384, "y": 461}}, {"label": "person", "confidence": 0.11621653288602829, "topleft": {"x": 625, "y": 401}, "bottomright": {"x": 649, "y": 486}}, {"label": "bench", "confidence": 0.11620762199163437, "topleft": {"x": 473, "y": 520}, "bottomright": {"x": 656, "y": 679}}, {"label": "person", "confidence": 0.11409121006727219, "topleft": {"x": 478, "y": 384}, "bottomright": {"x": 504, "y": 427}}, {"label": "person", "confidence": 0.11246053129434586, "topleft": {"x": 499, "y": 382}, "bottomright": {"x": 522, "y": 413}}, {"label": "person", "confidence": 0.1120673418045044, "topleft": {"x": 1222, "y": 432}, "bottomright": {"x": 1255, "y": 479}}, {"label": "person", "confidence": 0.10548914968967438, "topleft": {"x": 1205, "y": 469}, "bottomright": {"x": 1238, "y": 551}}, {"label": "person", "confidence": 0.1044657975435257, "topleft": {"x": 472, "y": 395}, "bottomright": {"x": 484, "y": 415}}, {"label": "bench", "confidence": 0.10238395631313324, "topleft": {"x": 618, "y": 504}, "bottomright": {"x": 999, "y": 602}}]