[{"label": "car", "confidence": 0.8725660443305969, "topleft": {"x": 17, "y": 647}, "bottomright": {"x": 203, "y": 772}}, {"label": "car", "confidence": 0.8314666748046875, "topleft": {"x": 237, "y": 587}, "bottomright": {"x": 403, "y": 694}}, {"label": "car", "confidence": 0.8203305006027222, "topleft": {"x": 1440, "y": 485}, "bottomright": {"x": 1550, "y": 586}}, {"label": "car", "confidence": 0.6379773616790771, "topleft": {"x": 441, "y": 413}, "bottomright": {"x": 586, "y": 520}}, {"label": "car", "confidence": 0.6228317618370056, "topleft": {"x": 1207, "y": 466}, "bottomright": {"x": 1331, "y": 575}}, {"label": "car", "confidence": 0.6151357293128967, "topleft": {"x": 643, "y": 458}, "bottomright": {"x": 779, "y": 552}}, {"label": "car", "confidence": 0.6005606055259705, "topleft": {"x": 389, "y": 316}, "bottomright": {"x": 496, "y": 397}}, {"label": "car", "confidence": 0.5525886416435242, "topleft": {"x": 1331, "y": 40}, "bottomright": {"x": 1412, "y": 107}}, {"label": "car", "confidence": 0.5199479460716248, "topleft": {"x": 1075, "y": 230}, "bottomright": {"x": 1177, "y": 323}}, {"label": "car", "confidence": 0.45241716504096985, "topleft": {"x": 1020, "y": 24}, "bottomright": {"x": 1199, "y": 216}}, {"label": "car", "confidence": 0.4506593346595764, "topleft": {"x": 1366, "y": 359}, "bottomright": {"x": 1467, "y": 451}}, {"label": "car", "confidence": 0.3517697751522064, "topleft": {"x": 632, "y": 371}, "bottomright": {"x": 733, "y": 455}}, {"label": "car", "confidence": 0.3016037940979004, "topleft": {"x": 1764, "y": 74}, "bottomright": {"x": 1848, "y": 134}}, {"label": "car", "confidence": 0.29383963346481323, "topleft": {"x": 815, "y": 385}, "bottomright": {"x": 924, "y": 467}}, {"label": "car", "confidence": 0.2824876308441162, "topleft": {"x": 1224, "y": 10}, "bottomright": {"x": 1296, "y": 82}}, {"label": "car", "confidence": 0.25006160140037537, "topleft": {"x": 630, "y": 370}, "bottomright": {"x": 736, "y": 454}}, {"label": "car", "confidence": 0.2081693559885025, "topleft": {"x": 241, "y": 581}, "bottomright": {"x": 409, "y": 692}}, {"label": "car", "confidence": 0.18609778583049774, "topleft": {"x": 1552, "y": 205}, "bottomright": {"x": 1713, "y": 439}}, {"label": "car", "confidence": 0.16537615656852722, "topleft": {"x": 379, "y": 317}, "bottomright": {"x": 499, "y": 397}}, {"label": "car", "confidence": 0.15409645438194275, "topleft": {"x": 1366, "y": 359}, "bottomright": {"x": 1467, "y": 451}}, {"label": "car", "confidence": 0.135616272687912, "topleft": {"x": 639, "y": 459}, "bottomright": {"x": 782, "y": 550}}, {"label": "car", "confidence": 0.13267983496189117, "topleft": {"x": 1205, "y": 468}, "bottomright": {"x": 1338, "y": 571}}, {"label": "car", "confidence": 0.1321677714586258, "topleft": {"x": 12, "y": 646}, "bottomright": {"x": 209, "y": 773}}, {"label": "car", "confidence": 0.12215929478406906, "topleft": {"x": 1546, "y": 200}, "bottomright": {"x": 1711, "y": 438}}, {"label": "car", "confidence": 0.12050142884254456, "topleft": {"x": 441, "y": 413}, "bottomright": {"x": 586, "y": 520}}, {"label": "car", "confidence": 0.10614454746246338, "topleft": {"x": 630, "y": 370}, "bottomright": {"x": 736, "y": 454}}, {"label": "car", "confidence": 0.10255128890275955, "topleft": {"x": 814, "y": 29}, "bottomright": {"x": 971, "y": 263}}, {"label": "car", "confidence": 0.10151268541812897, "topleft": {"x": 1075, "y": 230}, "bottomright": {"x": 1177, "y": 323}}]