[{"label": "car", "confidence": 0.6753232479095459, "topleft": {"x": 570, "y": 479}, "bottomright": {"x": 700, "y": 578}}, {"label": "car", "confidence": 0.6621004343032837, "topleft": {"x": 186, "y": 487}, "bottomright": {"x": 346, "y": 615}}, {"label": "car", "confidence": 0.660860538482666, "topleft": {"x": 888, "y": 74}, "bottomright": {"x": 1105, "y": 296}}, {"label": "car", "confidence": 0.6509875059127808, "topleft": {"x": 1520, "y": 394}, "bottomright": {"x": 1621, "y": 487}}, {"label": "car", "confidence": 0.6281274557113647, "topleft": {"x": 365, "y": 561}, "bottomright": {"x": 518, "y": 660}}, {"label": "car", "confidence": 0.5275989174842834, "topleft": {"x": 1334, "y": 377}, "bottomright": {"x": 1447, "y": 465}}, {"label": "car", "confidence": 0.5235846638679504, "topleft": {"x": 896, "y": 321}, "bottomright": {"x": 1009, "y": 429}}, {"label": "car", "confidence": 0.5010941624641418, "topleft": {"x": 136, "y": 393}, "bottomright": {"x": 256, "y": 483}}, {"label": "car", "confidence": 0.48949745297431946, "topleft": {"x": 406, "y": 447}, "bottomright": {"x": 529, "y": 539}}, {"label": "car", "confidence": 0.46648725867271423, "topleft": {"x": 1606, "y": 136}, "bottomright": {"x": 1768, "y": 357}}, {"label": "car", "confidence": 0.36977681517601013, "topleft": {"x": 1150, "y": 62}, "bottomright": {"x": 1236, "y": 146}}, {"label": "car", "confidence": 0.3150489032268524, "topleft": {"x": 1236, "y": 127}, "bottomright": {"x": 1328, "y": 201}}, {"label": "car", "confidence": 0.29145243763923645, "topleft": {"x": 1486, "y": 264}, "bottomright": {"x": 1574, "y": 343}}, {"label": "car", "confidence": 0.2827032208442688, "topleft": {"x": 631, "y": 311}, "bottomright": {"x": 776, "y": 451}}, {"label": "car", "confidence": 0.2555917501449585, "topleft": {"x": 1606, "y": 136}, "bottomright": {"x": 1768, "y": 357}}, {"label": "car", "confidence": 0.24655909836292267, "topleft": {"x": 631, "y": 311}, "bottomright": {"x": 776, "y": 451}}, {"label": "car", "confidence": 0.24122661352157593, "topleft": {"x": 569, "y": 480}, "bottomright": {"x": 699, "y": 575}}, {"label": "car", "confidence": 0.22344914078712463, "topleft": {"x": 406, "y": 447}, "bottomright": {"x": 529, "y": 539}}, {"label": "car", "confidence": 0.21718785166740417, "topleft": {"x": 189, "y": 492}, "bottomright": {"x": 340, "y": 615}}, {"label": "car", "confidence": 0.21587082743644714, "topleft": {"x": 1640, "y": 75}, "bottomright": {"x": 1714, "y": 135}}, {"label": "car", "confidence": 0.1616625338792801, "topleft": {"x": 1804, "y": 25}, "bottomright": {"x": 1868, "y": 64}}, {"label": "car", "confidence": 0.14535604417324066, "topleft": {"x": 888, "y": 74}, "bottomright": {"x": 1105, "y": 296}}, {"label": "car", "confidence": 0.14412198960781097, "topleft": {"x": 896, "y": 321}, "bottomright": {"x": 1009, "y": 429}}, {"label": "car", "confidence": 0.14223700761795044, "topleft": {"x": 1251, "y": 100}, "bottomright": {"x": 1279, "y": 126}}, {"label": "car", "confidence": 0.13573341071605682, "topleft": {"x": 1253, "y": 117}, "bottomright": {"x": 1298, "y": 150}}, {"label": "chair", "confidence": 0.13178817927837372, "topleft": {"x": 1626, "y": 146}, "bottomright": {"x": 1782, "y": 300}}, {"label": "car", "confidence": 0.12839223444461823, "topleft": {"x": 133, "y": 394}, "bottomright": {"x": 258, "y": 482}}, {"label": "car", "confidence": 0.1275051236152649, "topleft": {"x": 1334, "y": 377}, "bottomright": {"x": 1447, "y": 465}}, {"label": "car", "confidence": 0.12531432509422302, "topleft": {"x": 365, "y": 561}, "bottomright": {"x": 518, "y": 660}}, {"label": "car", "confidence": 0.1243937760591507, "topleft": {"x": 1150, "y": 62}, "bottomright": {"x": 1236, "y": 146}}, {"label": "car", "confidence": 0.12347470968961716, "topleft": {"x": 1520, "y": 394}, "bottomright": {"x": 1621, "y": 487}}, {"label": "car", "confidence": 0.11958473920822144, "topleft": {"x": 635, "y": 311}, "bottomright": {"x": 769, "y": 448}}, {"label": "car", "confidence": 0.11495855450630188, "topleft": {"x": 1420, "y": 406}, "bottomright": {"x": 1460, "y": 447}}, {"label": "car", "confidence": 0.10594462603330612, "topleft": {"x": 1279, "y": 92}, "bottomright": {"x": 1317, "y": 122}}]