[{"label": "car", "confidence": 0.8882614374160767, "topleft": {"x": 567, "y": 482}, "bottomright": {"x": 718, "y": 579}}, {"label": "car", "confidence": 0.8817153573036194, "topleft": {"x": 1268, "y": 645}, "bottomright": {"x": 1414, "y": 764}}, {"label": "car", "confidence": 0.7625508308410645, "topleft": {"x": 1414, "y": 343}, "bottomright": {"x": 1610, "y": 591}}, {"label": "car", "confidence": 0.761712372303009, "topleft": {"x": 996, "y": 294}, "bottomright": {"x": 1109, "y": 377}}, {"label": "car", "confidence": 0.6899742484092712, "topleft": {"x": 148, "y": 561}, "bottomright": {"x": 363, "y": 736}}, {"label": "car", "confidence": 0.6763221025466919, "topleft": {"x": 953, "y": 654}, "bottomright": {"x": 1108, "y": 779}}, {"label": "car", "confidence": 0.6123078465461731, "topleft": {"x": 801, "y": 286}, "bottomright": {"x": 926, "y": 379}}, {"label": "car", "confidence": 0.6111931204795837, "topleft": {"x": 708, "y": 424}, "bottomright": {"x": 840, "y": 512}}, {"label": "car", "confidence": 0.6040160655975342, "topleft": {"x": 703, "y": 184}, "bottomright": {"x": 794, "y": 250}}, {"label": "car", "confidence": 0.5513132810592651, "topleft": {"x": 1148, "y": 544}, "bottomright": {"x": 1276, "y": 644}}, {"label": "car", "confidence": 0.44799506664276123, "topleft": {"x": 1277, "y": 83}, "bottomright": {"x": 1364, "y": 159}}, {"label": "car", "confidence": 0.41650402545928955, "topleft": {"x": 911, "y": 240}, "bottomright": {"x": 1008, "y": 314}}, {"label": "car", "confidence": 0.3706505000591278, "topleft": {"x": 1121, "y": 219}, "bottomright": {"x": 1209, "y": 296}}, {"label": "car", "confidence": 0.3669048547744751, "topleft": {"x": 32, "y": 559}, "bottomright": {"x": 161, "y": 662}}, {"label": "car", "confidence": 0.2929697036743164, "topleft": {"x": 1427, "y": 432}, "bottomright": {"x": 1604, "y": 597}}, {"label": "car", "confidence": 0.2773582637310028, "topleft": {"x": 1148, "y": 542}, "bottomright": {"x": 1270, "y": 646}}, {"label": "car", "confidence": 0.2687254250049591, "topleft": {"x": 1676, "y": 231}, "bottomright": {"x": 1764, "y": 295}}, {"label": "car", "confidence": 0.1911189705133438, "topleft": {"x": 1043, "y": 115}, "bottomright": {"x": 1149, "y": 222}}, {"label": "car", "confidence": 0.18811018764972687, "topleft": {"x": 955, "y": 649}, "bottomright": {"x": 1114, "y": 781}}, {"label": "car", "confidence": 0.1794765293598175, "topleft": {"x": 1045, "y": 107}, "bottomright": {"x": 1150, "y": 228}}, {"label": "car", "confidence": 0.17594803869724274, "topleft": {"x": 36, "y": 557}, "bottomright": {"x": 188, "y": 658}}, {"label": "car", "confidence": 0.13594256341457367, "topleft": {"x": 708, "y": 424}, "bottomright": {"x": 840, "y": 512}}, {"label": "car", "confidence": 0.12943269312381744, "topleft": {"x": 800, "y": 288}, "bottomright": {"x": 927, "y": 379}}, {"label": "car", "confidence": 0.12831825017929077, "topleft": {"x": 1388, "y": 362}, "bottomright": {"x": 1450, "y": 419}}, {"label": "traffic", "confidence": 0.12321065366268158, "topleft": {"x": 259, "y": 344}, "bottomright": {"x": 308, "y": 420}}, {"label": "car", "confidence": 0.11933639645576477, "topleft": {"x": 137, "y": 606}, "bottomright": {"x": 368, "y": 736}}, {"label": "car", "confidence": 0.1126527264714241, "topleft": {"x": 491, "y": 956}, "bottomright": {"x": 1025, "y": 1067}}, {"label": "car", "confidence": 0.11202368885278702, "topleft": {"x": 612, "y": 468}, "bottomright": {"x": 690, "y": 504}}, {"label": "person", "confidence": 0.10795916616916656, "topleft": {"x": 270, "y": 631}, "bottomright": {"x": 293, "y": 656}}, {"label": "car", "confidence": 0.10679925233125687, "topleft": {"x": 679, "y": 453}, "bottomright": {"x": 742, "y": 504}}, {"label": "car", "confidence": 0.10188635438680649, "topleft": {"x": 1045, "y": 107}, "bottomright": {"x": 1150, "y": 228}}]